unityproxy/__init__.py
unityproxy/exceptions/__init__.py
unityproxy/exceptions/invalid_params.py
unityproxy/types/__init__.py
unityproxy/types/proxy_types.py
unityproxy/utils/__init__.py
unityproxy/utils/data_output.py
unityproxy/utils/proxy.py
unityproxy/utils/unity.py
unityproxy/utils/validator.py
UnityProxy-0.0.1.dist-info/LICENSE
UnityProxy-0.0.1.dist-info/METADATA
UnityProxy-0.0.1.dist-info/WHEEL
UnityProxy-0.0.1.dist-info/top_level.txt
UnityProxy-0.0.1.dist-info/RECORD
