Metadata-Version: 2.1
Name: UnityProxy
Version: 0.0.1
Summary: Proxy parser and converter
Home-page: https://github.com/mrsmori/unityproxy
Author: Lisica
Author-email: nomail@google.com
Classifier: Programming Language :: Python :: 3
Classifier: License :: OSI Approved :: MIT License
Classifier: Operating System :: OS Independent
License-File: LICENSE
